Metadata-Version: 2.1
Name: Outlier-Removal-101883059-Priyanshu-Tuli
Version: 0.0.1
Summary: A package for removing the outliers from a dataset using Z score
Home-page: https://github.com/Priyanshu0/Outlier-Removal-Using-Z-score
Author: Priyanshu Tuli
Author-email: priyanshu1tuli@gmail.com
License: UNKNOWN
Platform: UNKNOWN
Classifier: Programming Language :: Python :: 3
Classifier: License :: OSI Approved :: MIT License
Classifier: Operating System :: OS Independent
Requires-Python: >=3.6
